setup.py
visualisedictionary/__init__.py
visualisedictionary/print_keys.py
visualisedictionary/visualise_keys.py
visualisedictionary.egg-info/PKG-INFO
visualisedictionary.egg-info/SOURCES.txt
visualisedictionary.egg-info/dependency_links.txt
visualisedictionary.egg-info/requires.txt
visualisedictionary.egg-info/top_level.txt