Metadata-Version: 1.0
Name: visualisedictionary
Version: 0.1.1
Summary: visualisedictionary provides a pretty print for nested dictionary keys, as well as a pygraphviz plotter.
Home-page: UNKNOWN
Author: Alex Warwick Vesztrocy
Author-email: alex.warwick.vesztrocy.15@ucl.ac.uk
License: UNKNOWN
Platform: UNKNOWN
